wellmap/__init__.py
wellmap/file.py
wellmap/plot.py
wellmap/util.py
wellmap/.ruff_cache/.gitignore
wellmap/.ruff_cache/CACHEDIR.TAG
wellmap/.ruff_cache/content/14dd77c9dfd78f66
wellmap/.ruff_cache/content/8187be42fcb53812
wellmap/.ruff_cache/content/abf0aa791b08b83e
wellmap/.ruff_cache/content/b08eb1e3a314c456
wellmap-3.5.2.dist-info/entry_points.txt
wellmap-3.5.2.dist-info/WHEEL
wellmap-3.5.2.dist-info/METADATA
wellmap-3.5.2.dist-info/RECORD
