Metadata-Version: 2.1
Name: wellmap
Version: 3.5.2
Summary: File format for 96-well plate layouts.
Author-email: Kale Kundert <kale@thekunderts.net>
Requires-Python: ~=3.7
Classifier: Programming Language :: Python :: 3.7
Requires-Dist: pandas
Requires-Dist: tomli >= 1.1.0 ; python_version < "3.11"
Requires-Dist: typing-extensions; python_version < "3.9"
Requires-Dist: inform >= 1.15
Requires-Dist: docopt
Requires-Dist: matplotlib
Requires-Dist: colorcet
Requires-Dist: sphinx==5.3.0 ; extra == "doc"
Requires-Dist: sphinx-rtd-theme==1.3.0 ; extra == "doc"
Requires-Dist: sphinxcontrib-programoutput==0.17 ; extra == "doc"
Requires-Dist: sphinx-issues==3.0.1 ; extra == "doc"
Requires-Dist: myst-parser==1.0.0 ; extra == "doc"
Requires-Dist: pytest==7.4.2 ; extra == "test"
Requires-Dist: pytest-cov==4.1.0 ; extra == "test"
Requires-Dist: pytest-subtests==0.11.0 ; extra == "test"
Requires-Dist: pytest-unordered==0.5.2 ; extra == "test"
Requires-Dist: parametrize_from_file==0.18.0 ; extra == "test"
Requires-Dist: hypothesis==6.79.4 ; extra == "test"
Requires-Dist: coveralls ; extra == "test"
Project-URL: Bug Tracker, https://github.com/kalekundert/wellmap/issues
Project-URL: Continuous Integration, https://travis-ci.org/kalekundert/wellmap
Project-URL: Documentation, https://wellmap.readthedocs.io/en/latest/
Project-URL: Test Coverage, https://coveralls.io/github/kalekundert/wellmap
Project-URL: Version Control, https://github.com/kalekundert/wellmap
Provides-Extra: doc
Provides-Extra: test
